recgov/__init__.py
recgov/_requests.py
recgov/availability.py
recgov/campsites.py
recgov/test_campsites.py
recgov/test_utils.py
recgov/utils.py
recgov-0.1.4.dist-info/LICENSE.txt
recgov-0.1.4.dist-info/METADATA
recgov-0.1.4.dist-info/WHEEL
recgov-0.1.4.dist-info/top_level.txt
recgov-0.1.4.dist-info/RECORD
