Metadata-Version: 2.1
Name: recgov
Version: 0.1.4
Summary: A library to facilitate querying data from recreation.gov
Home-page: UNKNOWN
License: MIT License
Keywords: api,recreation
Platform: UNKNOWN
Classifier: License :: OSI Approved :: MIT License
Classifier: Programming Language :: Python :: 3
Classifier: Programming Language :: Python :: 3.7
Requires-Dist: requests
Requires-Dist: python-dateutil
Requires-Dist: fake-useragent
